paraconsistent/__init__.py
paraconsistent/py.typed
paraconsistent/blocks/__init__.py
paraconsistent/blocks/block.py
paraconsistent/core/__init__.py
paraconsistent/core/config.py
paraconsistent/core/engine.py
paraconsistent/core/labels.py
paraconsistent/core/metrics.py
paraconsistent/core/types.py
paraconsistent/examples/demo_wiring.py
paraconsistent-0.2.4.dist-info/METADATA
paraconsistent-0.2.4.dist-info/WHEEL
paraconsistent-0.2.4.dist-info/top_level.txt
paraconsistent-0.2.4.dist-info/RECORD
