Metadata-Version: 2.4
Name: paraconsistent
Version: 0.2.4
Summary: Blocos de lógica paraconsistente com API simples.
Author-email: Diego <diego263526352635@gmail.com>
Keywords: logic,paraconsistent,LPA2v,reasoning,fuzzy
Classifier: Programming Language :: Python :: 3 :: Only
Classifier: Programming Language :: Python :: 3.9
Classifier: Programming Language :: Python :: 3.10
Classifier: Programming Language :: Python :: 3.11
Classifier: Programming Language :: Python :: 3.12
Classifier: License :: OSI Approved :: MIT License
Classifier: Operating System :: OS Independent
Classifier: Typing :: Typed
Requires-Python: >=3.9
